devpi_process/__init__.py
devpi_process/_version.py
devpi_process/py.typed
devpi_process-1.1.0.dist-info/METADATA
devpi_process-1.1.0.dist-info/WHEEL
devpi_process-1.1.0.dist-info/licenses/LICENSE.txt
devpi_process-1.1.0.dist-info/RECORD
