Metadata-Version: 2.4
Name: devpi-process
Version: 1.1.0
Summary: devpi process provides a programmatic API to create and use a devpi server process
Project-URL: Homepage, https://github.com/tox-dev/devpi-process#readme
Project-URL: Source, https://github.com/tox-dev/devpi-process
Project-URL: Tracker, https://github.com/tox-dev/devpi-process/issues
Author-email: Bernát Gábor <gaborjbernat@gmail.com>
Maintainer-email: Bernát Gábor <gaborjbernat@gmail.com>
License-Expression: MIT
License-File: LICENSE.txt
Keywords: environments,isolated,testing,virtual
Classifier: Development Status :: 5 - Production/Stable
Classifier: Framework :: tox
Classifier: Intended Audience :: Developers
Classifier: License :: OSI Approved :: MIT License
Classifier: Operating System :: MacOS :: MacOS X
Classifier: Operating System :: Microsoft :: Windows
Classifier: Operating System :: POSIX
Classifier: Programming Language :: Python :: 3 :: Only
Classifier: Programming Language :: Python :: 3.10
Classifier: Programming Language :: Python :: 3.11
Classifier: Programming Language :: Python :: 3.12
Classifier: Programming Language :: Python :: 3.13
Classifier: Topic :: Software Development :: Libraries
Classifier: Topic :: Software Development :: Testing
Classifier: Topic :: Utilities
Requires-Python: >=3.10
Requires-Dist: devpi-client>=7.2
Requires-Dist: devpi-server>=6.17
Requires-Dist: typing-extensions>=4.15; python_version < '3.11'
Provides-Extra: testing
Requires-Dist: covdefaults>=2.3; extra == 'testing'
Requires-Dist: httpx>=0.28.1; extra == 'testing'
Requires-Dist: pytest-cov>=7; extra == 'testing'
Requires-Dist: pytest>=8.4.2; extra == 'testing'
